myvenv/__init__.py
myvenv-0.1.0.data/scripts/myvenv.bat
myvenv-0.1.0.dist-info/METADATA
myvenv-0.1.0.dist-info/WHEEL
myvenv-0.1.0.dist-info/top_level.txt
myvenv-0.1.0.dist-info/RECORD
