Metadata-Version: 2.2
Name: myvenv
Version: 0.1.0
Summary: A simple Windows utility to create or activate a Python virtual environment in the current CMD shell.
Home-page: https://github.com/ILikeAI/myvenv
Author: ILikeAI
Author-email: joshlikesai@gmail.com
License: MIT
Classifier: Programming Language :: Python :: 3
Classifier: Operating System :: Microsoft :: Windows
Classifier: License :: OSI Approved :: MIT License
Requires-Python: >=3.6
Dynamic: author
Dynamic: author-email
Dynamic: classifier
Dynamic: description
Dynamic: description-content-type
Dynamic: home-page
Dynamic: license
Dynamic: requires-python
Dynamic: summary
